thc_MG_env/__init__.py
thc_MG_env/envs/__init__.py
thc_MG_env/envs/env_thc.py
thc_MG_env-0.0.4.dist-info/METADATA
thc_MG_env-0.0.4.dist-info/WHEEL
thc_MG_env-0.0.4.dist-info/top_level.txt
thc_MG_env-0.0.4.dist-info/RECORD
