Metadata-Version: 2.1
Name: thc_MG_env
Version: 0.0.4
Summary: model of MGs
Requires-Dist: gym
Requires-Dist: gymnasium
